[{
    "model": "userprofiles.user",
    "pk": "alejomarti",
    "fields": {
        "password": "pbkdf2_sha256$30000$nkZmY9bhbzYH$22sTRHZSZhsJVyD9tZ/L/uMs6lPQX1evfjaKxjpdRgc=",
        "last_login": null,
        "is_superuser": false,
        "first_name": "",
        "last_name": "",
        "age": null,
        "photo": "avatars/alejomarti.png",
        "sex": "",
        "is_player": true,
        "email": "alejo.marti@email.com",
        "is_staff": true,
        "is_active": true,
        "date_joined": "2017-01-21T05:03:15.349Z",
        "position": "",
        "weight": null,
        "height": null,
        "nickname": "More",
        "number_matches": null,
        "accomplished_matches": null,
        "time_available": "",
        "leg_profile": "",
        "number_shirt_preferred": "",
        "team_support": "",
        "player_preferred": "",
        "groups": [],
        "user_permissions": [],
        "team": []
    }
}, {
    "model": "userprofiles.user",
    "pk": "Benji",
    "fields": {
        "password": "160116",
        "last_login": null,
        "is_superuser": true,
        "first_name": "Benji",
        "last_name": "Price",
        "age": 30,
        "photo": "avatars/Benji.png",
        "sex": "Masculino",
        "is_player": true,
        "email": "benji@gmail.com",
        "is_staff": true,
        "is_active": true,
        "date_joined": "2017-01-11T13:58:51.955Z",
        "position": "Portero",
        "weight": "70.00",
        "height": "180.00",
        "nickname": "Benji Price",
        "number_matches": null,
        "accomplished_matches": null,
        "time_available": "Domingo",
        "leg_profile": "Ambidiestro",
        "number_shirt_preferred": "1",
        "team_support": "Niupi",
        "player_preferred": "Oliver",
        "groups": [],
        "user_permissions": [],
        "team": []
    }
}, {
    "model": "userprofiles.user",
    "pk": "Bluse",
    "fields": {
        "password": "160116",
        "last_login": null,
        "is_superuser": true,
        "first_name": "Bluse",
        "last_name": "Martinez",
        "age": 30,
        "photo": "avatars/Bluse.png",
        "sex": "Masculino",
        "is_player": true,
        "email": "bluse@gmail.con",
        "is_staff": true,
        "is_active": true,
        "date_joined": "2017-01-17T20:44:11.483Z",
        "position": "Defensa Central",
        "weight": "65.00",
        "height": "170.00",
        "nickname": "Bruce",
        "number_matches": null,
        "accomplished_matches": null,
        "time_available": "Domingo",
        "leg_profile": "Derecho",
        "number_shirt_preferred": "2",
        "team_support": "Nacional",
        "player_preferred": "Borja",
        "groups": [],
        "user_permissions": [],
        "team": []
    }
}, {
    "model": "userprofiles.user",
    "pk": "erick",
    "fields": {
        "password": "pbkdf2_sha256$30000$ySE80uf122WN$dozraThWyUpNie5JOyq5E1+Bx76uB/sGiJ2M4YBeeG0=",
        "last_login": null,
        "is_superuser": false,
        "first_name": "Erick",
        "last_name": "Canton\u00e1",
        "age": null,
        "photo": "",
        "sex": "False",
        "is_player": false,
        "email": "erick@lafrance.com",
        "is_staff": false,
        "is_active": false,
        "date_joined": "2017-01-24T23:59:03.257Z",
        "position": null,
        "weight": null,
        "height": null,
        "nickname": "",
        "number_matches": null,
        "accomplished_matches": null,
        "time_available": "",
        "leg_profile": "",
        "number_shirt_preferred": "",
        "team_support": "",
        "player_preferred": "",
        "groups": [],
        "user_permissions": [],
        "team": []
    }
}, {
    "model": "userprofiles.user",
    "pk": "fichaje",
    "fields": {
        "password": "ficha2312",
        "last_login": "2017-01-05T14:13:54.431Z",
        "is_superuser": true,
        "first_name": "Fichaje",
        "last_name": "Fuppbol",
        "age": null,
        "photo": "avatars/Fichaje.png",
        "sex": "",
        "is_player": false,
        "email": "contacto@fichaje.org",
        "is_staff": true,
        "is_active": true,
        "date_joined": "2016-11-13T23:42:59.807Z",
        "position": "Representante",
        "weight": null,
        "height": null,
        "nickname": "Fichaje",
        "number_matches": null,
        "accomplished_matches": null,
        "time_available": "",
        "leg_profile": "",
        "number_shirt_preferred": "",
        "team_support": "",
        "player_preferred": "",
        "groups": [],
        "user_permissions": [],
        "team": []
    }
}, {
    "model": "userprofiles.user",
    "pk": "giraldoesteban",
    "fields": {
        "password": "pbkdf2_sha256$30000$njrCLT3DKJ1f$vSsQkrPCPeFL9ffC0QGgYZJciqW3nrkq1p7+1/txRYM=",
        "last_login": null,
        "is_superuser": false,
        "first_name": "",
        "last_name": "",
        "age": 32,
        "photo": "avatars/giraldoesteban.png",
        "sex": "Masculino",
        "is_player": false,
        "email": "giraldoesteban@hotmail.com",
        "is_staff": false,
        "is_active": true,
        "date_joined": "2017-01-22T14:19:09.335Z",
        "position": "Centrocampista",
        "weight": "65.00",
        "height": "179.00",
        "nickname": "Flaco",
        "number_matches": null,
        "accomplished_matches": null,
        "time_available": "Domingo",
        "leg_profile": "Derecho",
        "number_shirt_preferred": "7",
        "team_support": "DIM",
        "player_preferred": "Valderrama",
        "groups": [],
        "user_permissions": [],
        "team": []
    }
}, {
    "model": "userprofiles.user",
    "pk": "jcsalaz",
    "fields": {
        "password": "pbkdf2_sha256$30000$Mc7eC8v6Mocb$X+lGgchynz4G9vXNZ/NwwDoihrXfcZMNSSysd4zshVM=",
        "last_login": null,
        "is_superuser": true,
        "first_name": "",
        "last_name": "",
        "age": 30,
        "photo": "avatars/jcsalaz.png",
        "sex": "Masculino",
        "is_player": true,
        "email": "jcsalaz@gmail.com",
        "is_staff": true,
        "is_active": true,
        "date_joined": "2017-01-21T18:32:14.140Z",
        "position": "Delantero",
        "weight": "75.00",
        "height": "170.00",
        "nickname": "Juan Camilo",
        "number_matches": null,
        "accomplished_matches": null,
        "time_available": "Domingo",
        "leg_profile": "Derecho",
        "number_shirt_preferred": "10",
        "team_support": "Nacional",
        "player_preferred": "Riquelme",
        "groups": [],
        "user_permissions": [],
        "team": []
    }
}, {
    "model": "userprofiles.user",
    "pk": "mike",
    "fields": {
        "password": "pbkdf2_sha256$30000$Efux1Q3zOeFN$fmXQeHdhgJbIXVik4ZKdzJCmSPJZc025FoKGgOtK6MQ=",
        "last_login": null,
        "is_superuser": true,
        "first_name": "",
        "last_name": "",
        "age": 98,
        "photo": "avatars/mike.png",
        "sex": "Masculino",
        "is_player": true,
        "email": "mike@gmail.com",
        "is_staff": true,
        "is_active": true,
        "date_joined": "2017-01-24T00:56:41.208Z",
        "position": "Lateral Derecho",
        "weight": "45.00",
        "height": "134.00",
        "nickname": "Wasowski",
        "number_matches": null,
        "accomplished_matches": null,
        "time_available": "Domingo",
        "leg_profile": "Ambidiestro",
        "number_shirt_preferred": "43",
        "team_support": "Monster Inc",
        "player_preferred": "Sullivan",
        "groups": [],
        "user_permissions": [],
        "team": []
    }
}, {
    "model": "userprofiles.user",
    "pk": "nuevo",
    "fields": {
        "password": "pbkdf2_sha256$30000$TGHwm6nKODEZ$yXVRdzqaS4QoYNCjIKvVEP8x/mNmb9Q55zNkZ7JMJ9k=",
        "last_login": "2017-01-21T04:39:54.731Z",
        "is_superuser": false,
        "first_name": "",
        "last_name": "",
        "age": null,
        "photo": "avatars/nuevo.png",
        "sex": "Masculino",
        "is_player": true,
        "email": "nuevo@gmail.com",
        "is_staff": true,
        "is_active": true,
        "date_joined": "2017-01-20T17:52:46.878Z",
        "position": "",
        "weight": null,
        "height": null,
        "nickname": "nuevo",
        "number_matches": null,
        "accomplished_matches": null,
        "time_available": "",
        "leg_profile": "",
        "number_shirt_preferred": "",
        "team_support": "",
        "player_preferred": "",
        "groups": [],
        "user_permissions": [],
        "team": []
    }
}, {
    "model": "userprofiles.user",
    "pk": "Oliver",
    "fields": {
        "password": "160116",
        "last_login": null,
        "is_superuser": false,
        "first_name": "Oliver",
        "last_name": "Atom",
        "age": 30,
        "photo": "avatars/Oliver.png",
        "sex": "Masculino",
        "is_player": false,
        "email": "oliver@gmail.com",
        "is_staff": false,
        "is_active": false,
        "date_joined": "2017-01-17T20:42:03.942Z",
        "position": "Delantero",
        "weight": "70.00",
        "height": "180.00",
        "nickname": "Oliver",
        "number_matches": null,
        "accomplished_matches": null,
        "time_available": "Domingo",
        "leg_profile": "Derecho",
        "number_shirt_preferred": "10",
        "team_support": "Barcelona",
        "player_preferred": "Messi",
        "groups": [],
        "user_permissions": [],
        "team": []
    }
}, {
    "model": "userprofiles.user",
    "pk": "paoc",
    "fields": {
        "password": "pbkdf2_sha256$30000$NQTWPJgUW0dH$nCNNRkb4SSND5bw6m9Ig60Eie0vUNwmX8yh6BOjjb34=",
        "last_login": null,
        "is_superuser": true,
        "first_name": "",
        "last_name": "",
        "age": 33,
        "photo": "avatars/paoc.png",
        "sex": "Femenino",
        "is_player": true,
        "email": "paoc@gmail.com",
        "is_staff": true,
        "is_active": true,
        "date_joined": "2017-01-21T21:59:11.182Z",
        "position": "Centrocampista",
        "weight": "67.00",
        "height": "1.73",
        "nickname": "pola",
        "number_matches": null,
        "accomplished_matches": null,
        "time_available": "Domingo",
        "leg_profile": "Derecho",
        "number_shirt_preferred": "7",
        "team_support": "Nacional",
        "player_preferred": "Borja",
        "groups": [],
        "user_permissions": [],
        "team": []
    }
}, {
    "model": "userprofiles.user",
    "pk": "samevivi",
    "fields": {
        "password": "pbkdf2_sha256$30000$k26H4DRtK629$yrDS2UQAmMZuOv0nWt2v+FfxkLDGt2uReIK1LQRUBI8=",
        "last_login": null,
        "is_superuser": false,
        "first_name": "",
        "last_name": "",
        "age": 27,
        "photo": "avatars/samevivi.png",
        "sex": "Femenino",
        "is_player": false,
        "email": "samevivi@gmail.com",
        "is_staff": false,
        "is_active": true,
        "date_joined": "2017-01-22T00:36:07.674Z",
        "position": "Lateral Izquierdo",
        "weight": "57.00",
        "height": "1.60",
        "nickname": "samevivi",
        "number_matches": null,
        "accomplished_matches": null,
        "time_available": "Domingo",
        "leg_profile": "Izquierdo",
        "number_shirt_preferred": "7",
        "team_support": "Real",
        "player_preferred": "james",
        "groups": [],
        "user_permissions": [],
        "team": []
    }
}, {
    "model": "userprofiles.user",
    "pk": "sanalejo04",
    "fields": {
        "password": "pbkdf2_sha256$30000$LbYpkt11NLKU$4QKOYhjnEpGoR8KoIEF45S+6guPAgfISDeXnedZzDOk=",
        "last_login": null,
        "is_superuser": false,
        "first_name": "",
        "last_name": "",
        "age": 30,
        "photo": "",
        "sex": "Masculino",
        "is_player": false,
        "email": "sanalejo04@hotmail.com",
        "is_staff": false,
        "is_active": true,
        "date_joined": "2017-01-26T20:21:24.494Z",
        "position": "Delantero",
        "weight": "78.00",
        "height": "176.00",
        "nickname": "Alejandro7k",
        "number_matches": null,
        "accomplished_matches": null,
        "time_available": "Domingo",
        "leg_profile": "Derecho",
        "number_shirt_preferred": "7",
        "team_support": "nacional",
        "player_preferred": "cristiano Ronaldo",
        "groups": [],
        "user_permissions": [],
        "team": ["F\u00fatbol Fun", "Manchester United"]
    }
}, {
    "model": "userprofiles.user",
    "pk": "Tom",
    "fields": {
        "password": "160116",
        "last_login": null,
        "is_superuser": false,
        "first_name": "Tom",
        "last_name": "Salazar",
        "age": 30,
        "photo": "avatars/Tom.png",
        "sex": "Masculino",
        "is_player": false,
        "email": "tom@gmail.com",
        "is_staff": false,
        "is_active": false,
        "date_joined": "2017-01-17T20:43:02.893Z",
        "position": "Media Punta",
        "weight": "70.00",
        "height": "180.00",
        "nickname": "Tom",
        "number_matches": null,
        "accomplished_matches": null,
        "time_available": "Domingo",
        "leg_profile": "Izquierdo",
        "number_shirt_preferred": "11",
        "team_support": "Madrid",
        "player_preferred": "James",
        "groups": [],
        "user_permissions": [],
        "team": []
    }
}]